kvdiff/__init__.py
kvdiff/kvdiff.py
kvdiff-0.2.5.dist-info/AUTHORS.md
kvdiff-0.2.5.dist-info/LICENSE
kvdiff-0.2.5.dist-info/METADATA
kvdiff-0.2.5.dist-info/WHEEL
kvdiff-0.2.5.dist-info/entry_points.txt
kvdiff-0.2.5.dist-info/top_level.txt
kvdiff-0.2.5.dist-info/RECORD
