Metadata-Version: 2.1
Name: kvdiff
Version: 0.2.5
Summary: Compare two text files by key columns
Home-page: https://github.com/dongyx/kvdiff
Author: DONG Yuxuan
Author-email: dong.yuxuan@outlook.com
License: MIT
Platform: UNKNOWN
Classifier: Programming Language :: Python :: 3
Classifier: License :: OSI Approved :: MIT License
Classifier: Operating System :: POSIX
Requires-Python: >=3.5
